phable/cache.py
phable/cli/__init__.py
phable/cli/assign.py
phable/cli/cache.py
phable/cli/comment.py
phable/cli/config.py
phable/cli/create.py
phable/cli/list.py
phable/cli/main.py
phable/cli/move.py
phable/cli/parent.py
phable/cli/report.py
phable/cli/show.py
phable/cli/status.py
phable/cli/subscribe.py
phable/cli/tag.py
phable/cli/utils.py
phable/config.py
phable/display.py
phable/phabricator.py
phable/task.py
phable/tests/conftest.py
phable/tests/fixtures/simple_task.json
phable/tests/phabricator_test.py
phable/utils.py
phable_cli-0.1.15.dist-info/METADATA
phable_cli-0.1.15.dist-info/WHEEL
phable_cli-0.1.15.dist-info/entry_points.txt
phable_cli-0.1.15.dist-info/licenses/LICENSE
phable_cli-0.1.15.dist-info/RECORD
