Metadata-Version: 2.4
Name: phable-cli
Version: 0.1.15
Summary: Manage Phabricator tasks from the comfort of your terminal
License: MIT
License-File: LICENSE
Author: Balthazar Rouberol
Author-email: br@imap.cc
Requires-Python: >=3.9,<4.0
Classifier: License :: OSI Approved :: MIT License
Classifier: Programming Language :: Python :: 3
Classifier: Programming Language :: Python :: 3.9
Classifier: Programming Language :: Python :: 3.10
Classifier: Programming Language :: Python :: 3.11
Classifier: Programming Language :: Python :: 3.12
Classifier: Programming Language :: Python :: 3.13
Classifier: Programming Language :: Python :: 3.14
Requires-Dist: click (>=8.1.8,<9.0.0)
Requires-Dist: pytest (>=8.3.5,<9.0.0)
Requires-Dist: requests (>=2.32.3,<3.0.0)
